{"page":350,"verses":[{"key":"24:1","chapter":24,"words":[{"id":"24:1:1","text":"سُورَةٌ","line":2,"type":"word"},{"id":"24:1:2","text":"أَنزَلۡنَٰهَا","line":2,"type":"word"},{"id":"24:1:3","text":"وَفَرَضۡنَٰهَا","line":2,"type":"word"},{"id":"24:1:4","text":"وَأَنزَلۡنَا","line":2,"type":"word"},{"id":"24:1:5","text":"فِيهَآ","line":2,"type":"word"},{"id":"24:1:6","text":"ءَايَٰتِۭ","line":2,"type":"word"},{"id":"24:1:7","text":"بَيِّنَٰتٖ","line":2,"type":"word"},{"id":"24:1:8","text":"لَّعَلَّكُمۡ","line":2,"type":"word"},{"id":"24:1:9","text":"تَذَكَّرُونَ","line":2,"type":"word"},{"id":"24:1:10","text":"١","line":3,"type":"end"}]},{"key":"24:2","chapter":24,"words":[{"id":"24:2:1","text":"ٱلزَّانِيَةُ","line":3,"type":"word"},{"id":"24:2:2","text":"وَٱلزَّانِي","line":3,"type":"word"},{"id":"24:2:3","text":"فَٱجۡلِدُواْ","line":3,"type":"word"},{"id":"24:2:4","text":"كُلَّ","line":3,"type":"word"},{"id":"24:2:5","text":"وَٰحِدٖ","line":3,"type":"word"},{"id":"24:2:6","text":"مِّنۡهُمَا","line":3,"type":"word"},{"id":"24:2:7","text":"مِاْئَةَ","line":3,"type":"word"},{"id":"24:2:8","text":"جَلۡدَةٖۖ","line":3,"type":"word"},{"id":"24:2:9","text":"وَلَا","line":3,"type":"word"},{"id":"24:2:10","text":"تَأۡخُذۡكُم","line":3,"type":"word"},{"id":"24:2:11","text":"بِهِمَا","line":4,"type":"word"},{"id":"24:2:12","text":"رَأۡفَةٞ","line":4,"type":"word"},{"id":"24:2:13","text":"فِي","line":4,"type":"word"},{"id":"24:2:14","text":"دِينِ","line":4,"type":"word"},{"id":"24:2:15","text":"ٱللَّهِ","line":4,"type":"word"},{"id":"24:2:16","text":"إِن","line":4,"type":"word"},{"id":"24:2:17","text":"كُنتُمۡ","line":4,"type":"word"},{"id":"24:2:18","text":"تُؤۡمِنُونَ","line":4,"type":"word"},{"id":"24:2:19","text":"بِٱللَّهِ","line":4,"type":"word"},{"id":"24:2:20","text":"وَٱلۡيَوۡمِ","line":4,"type":"word"},{"id":"24:2:21","text":"ٱلۡأٓخِرِۖ","line":4,"type":"word"},{"id":"24:2:22","text":"وَلۡيَشۡهَدۡ","line":4,"type":"word"},{"id":"24:2:23","text":"عَذَابَهُمَا","line":5,"type":"word"},{"id":"24:2:24","text":"طَآئِفَةٞ","line":5,"type":"word"},{"id":"24:2:25","text":"مِّنَ","line":5,"type":"word"},{"id":"24:2:26","text":"ٱلۡمُؤۡمِنِينَ","line":5,"type":"word"},{"id":"24:2:27","text":"٢","line":5,"type":"end"}]},{"key":"24:3","chapter":24,"words":[{"id":"24:3:1","text":"ٱلزَّانِي","line":5,"type":"word"},{"id":"24:3:2","text":"لَا","line":5,"type":"word"},{"id":"24:3:3","text":"يَنكِحُ","line":5,"type":"word"},{"id":"24:3:4","text":"إِلَّا","line":5,"type":"word"},{"id":"24:3:5","text":"زَانِيَةً","line":5,"type":"word"},{"id":"24:3:6","text":"أَوۡ","line":5,"type":"word"},{"id":"24:3:7","text":"مُشۡرِكَةٗ","line":5,"type":"word"},{"id":"24:3:8","text":"وَٱلزَّانِيَةُ","line":6,"type":"word"},{"id":"24:3:9","text":"لَا","line":6,"type":"word"},{"id":"24:3:10","text":"يَنكِحُهَآ","line":6,"type":"word"},{"id":"24:3:11","text":"إِلَّا","line":6,"type":"word"},{"id":"24:3:12","text":"زَانٍ","line":6,"type":"word"},{"id":"24:3:13","text":"أَوۡ","line":6,"type":"word"},{"id":"24:3:14","text":"مُشۡرِكٞۚ","line":6,"type":"word"},{"id":"24:3:15","text":"وَحُرِّمَ","line":6,"type":"word"},{"id":"24:3:16","text":"ذَٰلِكَ","line":6,"type":"word"},{"id":"24:3:17","text":"عَلَى","line":6,"type":"word"},{"id":"24:3:18","text":"ٱلۡمُؤۡمِنِينَ","line":6,"type":"word"},{"id":"24:3:19","text":"٣","line":7,"type":"end"}]},{"key":"24:4","chapter":24,"words":[{"id":"24:4:1","text":"وَٱلَّذِينَ","line":7,"type":"word"},{"id":"24:4:2","text":"يَرۡمُونَ","line":7,"type":"word"},{"id":"24:4:3","text":"ٱلۡمُحۡصَنَٰتِ","line":7,"type":"word"},{"id":"24:4:4","text":"ثُمَّ","line":7,"type":"word"},{"id":"24:4:5","text":"لَمۡ","line":7,"type":"word"},{"id":"24:4:6","text":"يَأۡتُواْ","line":7,"type":"word"},{"id":"24:4:7","text":"بِأَرۡبَعَةِ","line":7,"type":"word"},{"id":"24:4:8","text":"شُهَدَآءَ","line":7,"type":"word"},{"id":"24:4:9","text":"فَٱجۡلِدُوهُمۡ","line":8,"type":"word"},{"id":"24:4:10","text":"ثَمَٰنِينَ","line":8,"type":"word"},{"id":"24:4:11","text":"جَلۡدَةٗ","line":8,"type":"word"},{"id":"24:4:12","text":"وَلَا","line":8,"type":"word"},{"id":"24:4:13","text":"تَقۡبَلُواْ","line":8,"type":"word"},{"id":"24:4:14","text":"لَهُمۡ","line":8,"type":"word"},{"id":"24:4:15","text":"شَهَٰدَةً","line":8,"type":"word"},{"id":"24:4:16","text":"أَبَدٗاۚ","line":8,"type":"word"},{"id":"24:4:17","text":"وَأُوْلَٰٓئِكَ","line":8,"type":"word"},{"id":"24:4:18","text":"هُمُ","line":9,"type":"word"},{"id":"24:4:19","text":"ٱلۡفَٰسِقُونَ","line":9,"type":"word"},{"id":"24:4:20","text":"٤","line":9,"type":"end"}]},{"key":"24:5","chapter":24,"words":[{"id":"24:5:1","text":"إِلَّا","line":9,"type":"word"},{"id":"24:5:2","text":"ٱلَّذِينَ","line":9,"type":"word"},{"id":"24:5:3","text":"تَابُواْ","line":9,"type":"word"},{"id":"24:5:4","text":"مِنۢ","line":9,"type":"word"},{"id":"24:5:5","text":"بَعۡدِ","line":9,"type":"word"},{"id":"24:5:6","text":"ذَٰلِكَ","line":9,"type":"word"},{"id":"24:5:7","text":"وَأَصۡلَحُواْ","line":9,"type":"word"},{"id":"24:5:8","text":"فَإِنَّ","line":9,"type":"word"},{"id":"24:5:9","text":"ٱللَّهَ","line":10,"type":"word"},{"id":"24:5:10","text":"غَفُورٞ","line":10,"type":"word"},{"id":"24:5:11","text":"رَّحِيمٞ","line":10,"type":"word"},{"id":"24:5:12","text":"٥","line":10,"type":"end"}]},{"key":"24:6","chapter":24,"words":[{"id":"24:6:1","text":"وَٱلَّذِينَ","line":10,"type":"word"},{"id":"24:6:2","text":"يَرۡمُونَ","line":10,"type":"word"},{"id":"24:6:3","text":"أَزۡوَٰجَهُمۡ","line":10,"type":"word"},{"id":"24:6:4","text":"وَلَمۡ","line":10,"type":"word"},{"id":"24:6:5","text":"يَكُن","line":10,"type":"word"},{"id":"24:6:6","text":"لَّهُمۡ","line":10,"type":"word"},{"id":"24:6:7","text":"شُهَدَآءُ","line":11,"type":"word"},{"id":"24:6:8","text":"إِلَّآ","line":11,"type":"word"},{"id":"24:6:9","text":"أَنفُسُهُمۡ","line":11,"type":"word"},{"id":"24:6:10","text":"فَشَهَٰدَةُ","line":11,"type":"word"},{"id":"24:6:11","text":"أَحَدِهِمۡ","line":11,"type":"word"},{"id":"24:6:12","text":"أَرۡبَعُ","line":11,"type":"word"},{"id":"24:6:13","text":"شَهَٰدَٰتِۭ","line":11,"type":"word"},{"id":"24:6:14","text":"بِٱللَّهِ","line":11,"type":"word"},{"id":"24:6:15","text":"إِنَّهُۥ","line":11,"type":"word"},{"id":"24:6:16","text":"لَمِنَ","line":11,"type":"word"},{"id":"24:6:17","text":"ٱلصَّٰدِقِينَ","line":12,"type":"word"},{"id":"24:6:18","text":"٦","line":12,"type":"end"}]},{"key":"24:7","chapter":24,"words":[{"id":"24:7:1","text":"وَٱلۡخَٰمِسَةُ","line":12,"type":"word"},{"id":"24:7:2","text":"أَنَّ","line":12,"type":"word"},{"id":"24:7:3","text":"لَعۡنَتَ","line":12,"type":"word"},{"id":"24:7:4","text":"ٱللَّهِ","line":12,"type":"word"},{"id":"24:7:5","text":"عَلَيۡهِ","line":12,"type":"word"},{"id":"24:7:6","text":"إِن","line":12,"type":"word"},{"id":"24:7:7","text":"كَانَ","line":12,"type":"word"},{"id":"24:7:8","text":"مِنَ","line":12,"type":"word"},{"id":"24:7:9","text":"ٱلۡكَٰذِبِينَ","line":12,"type":"word"},{"id":"24:7:10","text":"٧","line":13,"type":"end"}]},{"key":"24:8","chapter":24,"words":[{"id":"24:8:1","text":"وَيَدۡرَؤُاْ","line":13,"type":"word"},{"id":"24:8:2","text":"عَنۡهَا","line":13,"type":"word"},{"id":"24:8:3","text":"ٱلۡعَذَابَ","line":13,"type":"word"},{"id":"24:8:4","text":"أَن","line":13,"type":"word"},{"id":"24:8:5","text":"تَشۡهَدَ","line":13,"type":"word"},{"id":"24:8:6","text":"أَرۡبَعَ","line":13,"type":"word"},{"id":"24:8:7","text":"شَهَٰدَٰتِۭ","line":13,"type":"word"},{"id":"24:8:8","text":"بِٱللَّهِ","line":13,"type":"word"},{"id":"24:8:9","text":"إِنَّهُۥ","line":13,"type":"word"},{"id":"24:8:10","text":"لَمِنَ","line":13,"type":"word"},{"id":"24:8:11","text":"ٱلۡكَٰذِبِينَ","line":14,"type":"word"},{"id":"24:8:12","text":"٨","line":14,"type":"end"}]},{"key":"24:9","chapter":24,"words":[{"id":"24:9:1","text":"وَٱلۡخَٰمِسَةَ","line":14,"type":"word"},{"id":"24:9:2","text":"أَنَّ","line":14,"type":"word"},{"id":"24:9:3","text":"غَضَبَ","line":14,"type":"word"},{"id":"24:9:4","text":"ٱللَّهِ","line":14,"type":"word"},{"id":"24:9:5","text":"عَلَيۡهَآ","line":14,"type":"word"},{"id":"24:9:6","text":"إِن","line":14,"type":"word"},{"id":"24:9:7","text":"كَانَ","line":14,"type":"word"},{"id":"24:9:8","text":"مِنَ","line":14,"type":"word"},{"id":"24:9:9","text":"ٱلصَّٰدِقِينَ","line":14,"type":"word"},{"id":"24:9:10","text":"٩","line":15,"type":"end"}]},{"key":"24:10","chapter":24,"words":[{"id":"24:10:1","text":"وَلَوۡلَا","line":15,"type":"word"},{"id":"24:10:2","text":"فَضۡلُ","line":15,"type":"word"},{"id":"24:10:3","text":"ٱللَّهِ","line":15,"type":"word"},{"id":"24:10:4","text":"عَلَيۡكُمۡ","line":15,"type":"word"},{"id":"24:10:5","text":"وَرَحۡمَتُهُۥ","line":15,"type":"word"},{"id":"24:10:6","text":"وَأَنَّ","line":15,"type":"word"},{"id":"24:10:7","text":"ٱللَّهَ","line":15,"type":"word"},{"id":"24:10:8","text":"تَوَّابٌ","line":15,"type":"word"},{"id":"24:10:9","text":"حَكِيمٌ","line":15,"type":"word"},{"id":"24:10:10","text":"١٠","line":15,"type":"end"}]}]}