{"page":165,"juz":10,"verses":[{"key":"8:47","chapter":8,"words":[{"id":"8:47:1","text":"وَلَا","line":16,"type":"word"},{"id":"8:47:2","text":"تَكُوۡنُوۡا","line":16,"type":"word"},{"id":"8:47:3","text":"كَالَّذِيۡنَ","line":16,"type":"word"},{"id":"8:47:4","text":"خَرَجُوۡا","line":16,"type":"word"},{"id":"8:47:5","text":"مِنۡ","line":16,"type":"word"},{"id":"8:47:6","text":"دِيَارِهِمۡ","line":1,"type":"word"},{"id":"8:47:7","text":"بَطَرًا","line":1,"type":"word"},{"id":"8:47:8","text":"وَّرِئَآءَ","line":1,"type":"word"},{"id":"8:47:9","text":"النَّاسِ","line":1,"type":"word"},{"id":"8:47:10","text":"وَ يَصُدُّوۡنَ","line":1,"type":"word"},{"id":"8:47:11","text":"عَنۡ","line":1,"type":"word"},{"id":"8:47:12","text":"سَبِيۡلِ","line":1,"type":"word"},{"id":"8:47:13","text":"اللّٰهِ​ؕ","line":1,"type":"word"},{"id":"8:47:14","text":"وَاللّٰهُ","line":2,"type":"word"},{"id":"8:47:15","text":"بِمَا","line":2,"type":"word"},{"id":"8:47:16","text":"يَعۡمَلُوۡنَ","line":2,"type":"word"},{"id":"8:47:17","text":"مُحِيۡطٌ‏ ﻿﻿","line":2,"type":"word"},{"id":"8:47:18","text":"٤٧","line":2,"type":"end"}]},{"key":"8:48","chapter":8,"words":[{"id":"8:48:1","text":"وَاِذۡ","line":2,"type":"word"},{"id":"8:48:2","text":"زَيَّنَ","line":2,"type":"word"},{"id":"8:48:3","text":"لَهُمُ","line":2,"type":"word"},{"id":"8:48:4","text":"الشَّيۡطٰنُ","line":2,"type":"word"},{"id":"8:48:5","text":"اَعۡمَالَهُمۡ","line":3,"type":"word"},{"id":"8:48:6","text":"وَقَالَ","line":3,"type":"word"},{"id":"8:48:7","text":"لَا","line":3,"type":"word"},{"id":"8:48:8","text":"غَالِبَ","line":3,"type":"word"},{"id":"8:48:9","text":"لَـكُمُ","line":3,"type":"word"},{"id":"8:48:10","text":"الۡيَوۡمَ","line":3,"type":"word"},{"id":"8:48:11","text":"مِنَ","line":3,"type":"word"},{"id":"8:48:12","text":"النَّاسِ","line":3,"type":"word"},{"id":"8:48:13","text":"وَاِنِّىۡ","line":3,"type":"word"},{"id":"8:48:14","text":"جَارٌ","line":4,"type":"word"},{"id":"8:48:15","text":"لَّـكُمۡ​ۚ","line":4,"type":"word"},{"id":"8:48:16","text":"فَلَمَّا","line":4,"type":"word"},{"id":"8:48:17","text":"تَرَآءَتِ","line":4,"type":"word"},{"id":"8:48:18","text":"الۡفِئَتٰنِ","line":4,"type":"word"},{"id":"8:48:19","text":"نَكَصَ","line":4,"type":"word"},{"id":"8:48:20","text":"عَلٰى","line":4,"type":"word"},{"id":"8:48:21","text":"عَقِبَيۡهِ","line":4,"type":"word"},{"id":"8:48:22","text":"وَقَالَ","line":4,"type":"word"},{"id":"8:48:23","text":"اِنِّىۡ","line":5,"type":"word"},{"id":"8:48:24","text":"بَرِىۡٓءٌ","line":5,"type":"word"},{"id":"8:48:25","text":"مِّنۡكُمۡ","line":5,"type":"word"},{"id":"8:48:26","text":"اِنِّىۡۤ","line":5,"type":"word"},{"id":"8:48:27","text":"اَرٰى","line":5,"type":"word"},{"id":"8:48:28","text":"مَا","line":5,"type":"word"},{"id":"8:48:29","text":"لَا","line":5,"type":"word"},{"id":"8:48:30","text":"تَرَوۡنَ","line":5,"type":"word"},{"id":"8:48:31","text":"اِنِّىۡۤ","line":5,"type":"word"},{"id":"8:48:32","text":"اَخَافُ","line":5,"type":"word"},{"id":"8:48:33","text":"اللّٰهَ​ؕ","line":5,"type":"word"},{"id":"8:48:34","text":"وَاللّٰهُ","line":6,"type":"word"},{"id":"8:48:35","text":"شَدِيۡدُ","line":6,"type":"word"},{"id":"8:48:36","text":"الۡعِقَابِ‏","line":6,"type":"word"},{"id":"8:48:37","text":"٤٨","line":6,"type":"end"}]},{"key":"8:49","chapter":8,"words":[{"id":"8:49:1","text":"اِذۡ","line":6,"type":"word"},{"id":"8:49:2","text":"يَقُوۡلُ","line":6,"type":"word"},{"id":"8:49:3","text":"الۡمُنٰفِقُوۡنَ","line":6,"type":"word"},{"id":"8:49:4","text":"وَالَّذِيۡنَ","line":6,"type":"word"},{"id":"8:49:5","text":"فِىۡ","line":7,"type":"word"},{"id":"8:49:6","text":"قُلُوۡبِهِمۡ","line":7,"type":"word"},{"id":"8:49:7","text":"مَّرَضٌ","line":7,"type":"word"},{"id":"8:49:8","text":"غَرَّ","line":7,"type":"word"},{"id":"8:49:9","text":"هٰٓؤُلَاۤءِ","line":7,"type":"word"},{"id":"8:49:10","text":"دِيۡنُهُمۡؕ","line":7,"type":"word"},{"id":"8:49:11","text":"وَمَنۡ","line":7,"type":"word"},{"id":"8:49:12","text":"يَّتَوَكَّلۡ","line":7,"type":"word"},{"id":"8:49:13","text":"عَلَى","line":8,"type":"word"},{"id":"8:49:14","text":"اللّٰهِ","line":8,"type":"word"},{"id":"8:49:15","text":"فَاِنَّ","line":8,"type":"word"},{"id":"8:49:16","text":"اللّٰهَ","line":8,"type":"word"},{"id":"8:49:17","text":"عَزِيۡزٌ","line":8,"type":"word"},{"id":"8:49:18","text":"حَكِيۡمٌ‏","line":8,"type":"word"},{"id":"8:49:19","text":"٤٩","line":8,"type":"end"}]},{"key":"8:50","chapter":8,"words":[{"id":"8:50:1","text":"وَ لَوۡ","line":8,"type":"word"},{"id":"8:50:2","text":"تَرٰٓى","line":8,"type":"word"},{"id":"8:50:3","text":"اِذۡ","line":8,"type":"word"},{"id":"8:50:4","text":"يَتَوَفَّى","line":8,"type":"word"},{"id":"8:50:5","text":"الَّذِيۡنَ","line":8,"type":"word"},{"id":"8:50:6","text":"كَفَرُوا​ ۙ","line":9,"type":"word"},{"id":"8:50:7","text":"الۡمَلٰٓٮِٕكَةُ","line":9,"type":"word"},{"id":"8:50:8","text":"يَضۡرِبُوۡنَ","line":9,"type":"word"},{"id":"8:50:9","text":"وُجُوۡهَهُمۡ","line":9,"type":"word"},{"id":"8:50:10","text":"وَاَدۡبَارَهُمۡۚ","line":9,"type":"word"},{"id":"8:50:11","text":"وَذُوۡقُوۡا","line":9,"type":"word"},{"id":"8:50:12","text":"عَذَابَ","line":10,"type":"word"},{"id":"8:50:13","text":"الۡحَرِيۡقِ‏","line":10,"type":"word"},{"id":"8:50:14","text":"٥٠","line":10,"type":"end"}]},{"key":"8:51","chapter":8,"words":[{"id":"8:51:1","text":"ذٰلِكَ","line":10,"type":"word"},{"id":"8:51:2","text":"بِمَا","line":10,"type":"word"},{"id":"8:51:3","text":"قَدَّمَتۡ","line":10,"type":"word"},{"id":"8:51:4","text":"اَيۡدِيۡكُمۡ","line":10,"type":"word"},{"id":"8:51:5","text":"وَاَنَّ","line":10,"type":"word"},{"id":"8:51:6","text":"اللّٰهَ","line":10,"type":"word"},{"id":"8:51:7","text":"لَـيۡسَ","line":10,"type":"word"},{"id":"8:51:8","text":"بِظَلَّامٍ","line":11,"type":"word"},{"id":"8:51:9","text":"لِّـلۡعَبِيۡدِۙ‏ ﻿﻿","line":11,"type":"word"},{"id":"8:51:10","text":"٥١","line":11,"type":"end"}]},{"key":"8:52","chapter":8,"words":[{"id":"8:52:1","text":"كَدَاۡبِ","line":11,"type":"word"},{"id":"8:52:2","text":"اٰلِ","line":11,"type":"word"},{"id":"8:52:3","text":"فِرۡعَوۡنَ​ۙ","line":11,"type":"word"},{"id":"8:52:4","text":"وَالَّذِيۡنَ","line":11,"type":"word"},{"id":"8:52:5","text":"مِنۡ","line":11,"type":"word"},{"id":"8:52:6","text":"قَبۡلِهِمۡ​ؕ","line":11,"type":"word"},{"id":"8:52:7","text":"كَفَرُوۡا","line":12,"type":"word"},{"id":"8:52:8","text":"بِاٰيٰتِ","line":12,"type":"word"},{"id":"8:52:9","text":"اللّٰهِ","line":12,"type":"word"},{"id":"8:52:10","text":"فَاَخَذَهُمُ","line":12,"type":"word"},{"id":"8:52:11","text":"اللّٰهُ","line":12,"type":"word"},{"id":"8:52:12","text":"بِذُنُوۡبِهِمۡ​ؕ","line":12,"type":"word"},{"id":"8:52:13","text":"اِنَّ","line":12,"type":"word"},{"id":"8:52:14","text":"اللّٰهَ","line":12,"type":"word"},{"id":"8:52:15","text":"قَوِىٌّ","line":12,"type":"word"},{"id":"8:52:16","text":"شَدِيۡدُ","line":13,"type":"word"},{"id":"8:52:17","text":"الۡعِقَابِ‏ ﻿﻿","line":13,"type":"word"},{"id":"8:52:18","text":"٥٢","line":13,"type":"end"}]},{"key":"8:53","chapter":8,"words":[{"id":"8:53:1","text":"ذٰلِكَ","line":13,"type":"word"},{"id":"8:53:2","text":"بِاَنَّ","line":13,"type":"word"},{"id":"8:53:3","text":"اللّٰهَ","line":13,"type":"word"},{"id":"8:53:4","text":"لَمۡ","line":13,"type":"word"},{"id":"8:53:5","text":"يَكُ","line":13,"type":"word"},{"id":"8:53:6","text":"مُغَيِّرًا","line":13,"type":"word"},{"id":"8:53:7","text":"نِّـعۡمَةً","line":13,"type":"word"},{"id":"8:53:8","text":"اَنۡعَمَهَا","line":14,"type":"word"},{"id":"8:53:9","text":"عَلٰى","line":14,"type":"word"},{"id":"8:53:10","text":"قَوۡمٍ","line":14,"type":"word"},{"id":"8:53:11","text":"حَتّٰى","line":14,"type":"word"},{"id":"8:53:12","text":"يُغَيِّرُوۡا","line":14,"type":"word"},{"id":"8:53:13","text":"مَا","line":14,"type":"word"},{"id":"8:53:14","text":"بِاَنۡفُسِهِمۡ​ۙ","line":14,"type":"word"},{"id":"8:53:15","text":"وَاَنَّ","line":14,"type":"word"},{"id":"8:53:16","text":"اللّٰهَ","line":14,"type":"word"},{"id":"8:53:17","text":"سَمِيۡعٌ","line":14,"type":"word"},{"id":"8:53:18","text":"عَلِيۡمٌۙ‏","line":15,"type":"word"},{"id":"8:53:19","text":"٥٣","line":15,"type":"end"}]},{"key":"8:54","chapter":8,"words":[{"id":"8:54:1","text":"كَدَاۡبِ","line":15,"type":"word"},{"id":"8:54:2","text":"اٰلِ","line":15,"type":"word"},{"id":"8:54:3","text":"فِرۡعَوۡنَ​ۙ","line":15,"type":"word"},{"id":"8:54:4","text":"وَالَّذِيۡنَ","line":15,"type":"word"},{"id":"8:54:5","text":"مِنۡ","line":15,"type":"word"},{"id":"8:54:6","text":"قَبۡلِهِمۡ​ؕ","line":15,"type":"word"},{"id":"8:54:7","text":"كَذَّبُوۡا","line":15,"type":"word"},{"id":"8:54:8","text":"بِاٰيٰتِ","line":16,"type":"word"},{"id":"8:54:9","text":"رَبِّهِمۡ","line":16,"type":"word"},{"id":"8:54:10","text":"فَاَهۡلَكۡنٰهُمۡ","line":16,"type":"word"},{"id":"8:54:11","text":"بِذُنُوۡبِهِمۡ","line":16,"type":"word"},{"id":"8:54:12","text":"وَاَغۡرَقۡنَاۤ","line":16,"type":"word"},{"id":"8:54:13","text":"اٰلَ","line":16,"type":"word"},{"id":"8:54:14","text":"فِرۡعَوۡنَ​ۚ","line":16,"type":"word"},{"id":"8:54:15","text":"وَكُلٌّ","line":1,"type":"word"},{"id":"8:54:16","text":"كَانُوۡا","line":1,"type":"word"},{"id":"8:54:17","text":"ظٰلِمِيۡنَ‏","line":1,"type":"word"},{"id":"8:54:18","text":"٥٤","line":1,"type":"end"}]}]}