{"page":211,"juz":12,"verses":[{"key":"11:111","chapter":11,"words":[{"id":"11:111:1","text":"وَاِنَّ","line":16,"type":"word"},{"id":"11:111:2","text":"كُلًّا","line":16,"type":"word"},{"id":"11:111:3","text":"لَّمَّا","line":16,"type":"word"},{"id":"11:111:4","text":"لَيُوَفِّيَنَّهُمۡ","line":16,"type":"word"},{"id":"11:111:5","text":"رَبُّكَ","line":16,"type":"word"},{"id":"11:111:6","text":"اَعۡمَالَهُمۡ​ ؕ","line":1,"type":"word"},{"id":"11:111:7","text":"اِنَّهٗ","line":1,"type":"word"},{"id":"11:111:8","text":"بِمَا","line":1,"type":"word"},{"id":"11:111:9","text":"يَعۡمَلُوۡنَ","line":1,"type":"word"},{"id":"11:111:10","text":"خَبِيۡرٌ‏","line":1,"type":"word"},{"id":"11:111:11","text":"١١١","line":1,"type":"end"}]},{"key":"11:112","chapter":11,"words":[{"id":"11:112:1","text":"فَاسۡتَقِمۡ","line":1,"type":"word"},{"id":"11:112:2","text":"كَمَاۤ","line":1,"type":"word"},{"id":"11:112:3","text":"اُمِرۡتَ","line":1,"type":"word"},{"id":"11:112:4","text":"وَمَنۡ","line":1,"type":"word"},{"id":"11:112:5","text":"تَابَ","line":1,"type":"word"},{"id":"11:112:6","text":"مَعَكَ","line":1,"type":"word"},{"id":"11:112:7","text":"وَلَا","line":2,"type":"word"},{"id":"11:112:8","text":"تَطۡغَوۡا​ ؕ","line":2,"type":"word"},{"id":"11:112:9","text":"اِنَّهٗ","line":2,"type":"word"},{"id":"11:112:10","text":"بِمَا","line":2,"type":"word"},{"id":"11:112:11","text":"تَعۡمَلُوۡنَ","line":2,"type":"word"},{"id":"11:112:12","text":"بَصِيۡرٌ‏","line":2,"type":"word"},{"id":"11:112:13","text":"١١٢","line":2,"type":"end"}]},{"key":"11:113","chapter":11,"words":[{"id":"11:113:1","text":"وَلَا","line":2,"type":"word"},{"id":"11:113:2","text":"تَرۡكَنُوۡۤا","line":2,"type":"word"},{"id":"11:113:3","text":"اِلَى","line":2,"type":"word"},{"id":"11:113:4","text":"الَّذِيۡنَ","line":2,"type":"word"},{"id":"11:113:5","text":"ظَلَمُوۡا","line":3,"type":"word"},{"id":"11:113:6","text":"فَتَمَسَّكُمُ","line":3,"type":"word"},{"id":"11:113:7","text":"النَّارُۙ","line":3,"type":"word"},{"id":"11:113:8","text":"وَمَا","line":3,"type":"word"},{"id":"11:113:9","text":"لَـكُمۡ","line":3,"type":"word"},{"id":"11:113:10","text":"مِّنۡ","line":3,"type":"word"},{"id":"11:113:11","text":"دُوۡنِ","line":3,"type":"word"},{"id":"11:113:12","text":"اللّٰهِ","line":3,"type":"word"},{"id":"11:113:13","text":"مِنۡ","line":3,"type":"word"},{"id":"11:113:14","text":"اَوۡلِيَآءَ","line":3,"type":"word"},{"id":"11:113:15","text":"ثُمَّ","line":4,"type":"word"},{"id":"11:113:16","text":"لَا","line":4,"type":"word"},{"id":"11:113:17","text":"تُنۡصَرُوۡنَ‏","line":4,"type":"word"},{"id":"11:113:18","text":"١١٣","line":4,"type":"end"}]},{"key":"11:114","chapter":11,"words":[{"id":"11:114:1","text":"وَاَقِمِ","line":4,"type":"word"},{"id":"11:114:2","text":"الصَّلٰوةَ","line":4,"type":"word"},{"id":"11:114:3","text":"طَرَفَىِ","line":4,"type":"word"},{"id":"11:114:4","text":"النَّهَارِ","line":4,"type":"word"},{"id":"11:114:5","text":"وَزُلَـفًا","line":4,"type":"word"},{"id":"11:114:6","text":"مِّنَ","line":4,"type":"word"},{"id":"11:114:7","text":"الَّيۡلِ​ ؕ","line":5,"type":"word"},{"id":"11:114:8","text":"اِنَّ","line":5,"type":"word"},{"id":"11:114:9","text":"الۡحَسَنٰتِ","line":5,"type":"word"},{"id":"11:114:10","text":"يُذۡهِبۡنَ","line":5,"type":"word"},{"id":"11:114:11","text":"السَّيِّاٰتِ ​ؕ","line":5,"type":"word"},{"id":"11:114:12","text":"ذٰ لِكَ","line":5,"type":"word"},{"id":"11:114:13","text":"ذِكۡرٰى","line":5,"type":"word"},{"id":"11:114:14","text":"لِلذّٰكِرِيۡنَ ​ۚ‏","line":5,"type":"word"},{"id":"11:114:15","text":"١١٤","line":5,"type":"end"}]},{"key":"11:115","chapter":11,"words":[{"id":"11:115:1","text":"وَاصۡبِرۡ","line":6,"type":"word"},{"id":"11:115:2","text":"فَاِنَّ","line":6,"type":"word"},{"id":"11:115:3","text":"اللّٰهَ","line":6,"type":"word"},{"id":"11:115:4","text":"لَا","line":6,"type":"word"},{"id":"11:115:5","text":"يُضِيۡعُ","line":6,"type":"word"},{"id":"11:115:6","text":"اَجۡرَ","line":6,"type":"word"},{"id":"11:115:7","text":"الۡمُحۡسِنِيۡنَ‏","line":6,"type":"word"},{"id":"11:115:8","text":"١١٥","line":6,"type":"end"}]},{"key":"11:116","chapter":11,"words":[{"id":"11:116:1","text":"فَلَوۡ لَا","line":6,"type":"word"},{"id":"11:116:2","text":"كَانَ","line":6,"type":"word"},{"id":"11:116:3","text":"مِنَ","line":7,"type":"word"},{"id":"11:116:4","text":"الۡقُرُوۡنِ","line":7,"type":"word"},{"id":"11:116:5","text":"مِنۡ","line":7,"type":"word"},{"id":"11:116:6","text":"قَبۡلِكُمۡ","line":7,"type":"word"},{"id":"11:116:7","text":"اُولُوۡا","line":7,"type":"word"},{"id":"11:116:8","text":"بَقِيَّةٍ","line":7,"type":"word"},{"id":"11:116:9","text":"يَّـنۡهَوۡنَ","line":7,"type":"word"},{"id":"11:116:10","text":"عَنِ","line":7,"type":"word"},{"id":"11:116:11","text":"الۡفَسَادِ","line":7,"type":"word"},{"id":"11:116:12","text":"فِى","line":8,"type":"word"},{"id":"11:116:13","text":"الۡاَرۡضِ","line":8,"type":"word"},{"id":"11:116:14","text":"اِلَّا","line":8,"type":"word"},{"id":"11:116:15","text":"قَلِيۡلًا","line":8,"type":"word"},{"id":"11:116:16","text":"مِّمَّنۡ","line":8,"type":"word"},{"id":"11:116:17","text":"اَنۡجَيۡنَا","line":8,"type":"word"},{"id":"11:116:18","text":"مِنۡهُمۡ​ ۚ","line":8,"type":"word"},{"id":"11:116:19","text":"وَاتَّبَعَ","line":8,"type":"word"},{"id":"11:116:20","text":"الَّذِيۡنَ","line":8,"type":"word"},{"id":"11:116:21","text":"ظَلَمُوۡا","line":8,"type":"word"},{"id":"11:116:22","text":"مَاۤ","line":9,"type":"word"},{"id":"11:116:23","text":"اُتۡرِفُوۡا","line":9,"type":"word"},{"id":"11:116:24","text":"فِيۡهِ","line":9,"type":"word"},{"id":"11:116:25","text":"وَكَانُوۡا","line":9,"type":"word"},{"id":"11:116:26","text":"مُجۡرِمِيۡنَ‏ ﻿﻿","line":9,"type":"word"},{"id":"11:116:27","text":"١١٦","line":9,"type":"end"}]},{"key":"11:117","chapter":11,"words":[{"id":"11:117:1","text":"وَمَا","line":9,"type":"word"},{"id":"11:117:2","text":"كَانَ","line":9,"type":"word"},{"id":"11:117:3","text":"رَبُّكَ","line":9,"type":"word"},{"id":"11:117:4","text":"لِيُهۡلِكَ","line":9,"type":"word"},{"id":"11:117:5","text":"الۡقُرٰى","line":9,"type":"word"},{"id":"11:117:6","text":"بِظُلۡمٍ","line":10,"type":"word"},{"id":"11:117:7","text":"وَّاَهۡلُهَا","line":10,"type":"word"},{"id":"11:117:8","text":"مُصۡلِحُوۡنَ‏ ﻿﻿","line":10,"type":"word"},{"id":"11:117:9","text":"١١٧","line":10,"type":"end"}]},{"key":"11:118","chapter":11,"words":[{"id":"11:118:1","text":"وَلَوۡ","line":10,"type":"word"},{"id":"11:118:2","text":"شَآءَ","line":10,"type":"word"},{"id":"11:118:3","text":"رَبُّكَ","line":10,"type":"word"},{"id":"11:118:4","text":"لَجَـعَلَ","line":10,"type":"word"},{"id":"11:118:5","text":"النَّاسَ","line":10,"type":"word"},{"id":"11:118:6","text":"اُمَّةً","line":11,"type":"word"},{"id":"11:118:7","text":"وَّاحِدَةً​","line":11,"type":"word"},{"id":"11:118:8","text":"وَّلَا","line":11,"type":"word"},{"id":"11:118:9","text":"يَزَالُوۡنَ","line":11,"type":"word"},{"id":"11:118:10","text":"مُخۡتَلِفِيۡنَۙ‏","line":11,"type":"word"},{"id":"11:118:11","text":"١١٨","line":11,"type":"end"}]},{"key":"11:119","chapter":11,"words":[{"id":"11:119:1","text":"اِلَّا","line":11,"type":"word"},{"id":"11:119:2","text":"مَنۡ","line":11,"type":"word"},{"id":"11:119:3","text":"رَّحِمَ","line":11,"type":"word"},{"id":"11:119:4","text":"رَبُّكَ​ ؕ","line":11,"type":"word"},{"id":"11:119:5","text":"وَلِذٰلِكَ","line":12,"type":"word"},{"id":"11:119:6","text":"خَلَقَهُمۡ​ ؕ","line":12,"type":"word"},{"id":"11:119:7","text":"وَتَمَّتۡ","line":12,"type":"word"},{"id":"11:119:8","text":"كَلِمَةُ","line":12,"type":"word"},{"id":"11:119:9","text":"رَبِّكَ","line":12,"type":"word"},{"id":"11:119:10","text":"لَاَمۡلَـئَنَّ","line":12,"type":"word"},{"id":"11:119:11","text":"جَهَـنَّمَ","line":12,"type":"word"},{"id":"11:119:12","text":"مِنَ","line":12,"type":"word"},{"id":"11:119:13","text":"الۡجِنَّةِ","line":13,"type":"word"},{"id":"11:119:14","text":"وَالنَّاسِ","line":13,"type":"word"},{"id":"11:119:15","text":"اَجۡمَعِيۡنَ‏","line":13,"type":"word"},{"id":"11:119:16","text":"١١٩","line":13,"type":"end"}]},{"key":"11:120","chapter":11,"words":[{"id":"11:120:1","text":"وَكُلًّا","line":13,"type":"word"},{"id":"11:120:2","text":"نَّقُصُّ","line":13,"type":"word"},{"id":"11:120:3","text":"عَلَيۡكَ","line":13,"type":"word"},{"id":"11:120:4","text":"مِنۡ","line":13,"type":"word"},{"id":"11:120:5","text":"اَنۡۢبَآءِ","line":13,"type":"word"},{"id":"11:120:6","text":"الرُّسُلِ","line":14,"type":"word"},{"id":"11:120:7","text":"مَا","line":14,"type":"word"},{"id":"11:120:8","text":"نُثَبِّتُ","line":14,"type":"word"},{"id":"11:120:9","text":"بِهٖ","line":14,"type":"word"},{"id":"11:120:10","text":"فُؤَادَكَ​ ۚ","line":14,"type":"word"},{"id":"11:120:11","text":"وَجَآءَكَ","line":14,"type":"word"},{"id":"11:120:12","text":"فِىۡ","line":14,"type":"word"},{"id":"11:120:13","text":"هٰذِهِ","line":14,"type":"word"},{"id":"11:120:14","text":"الۡحَـقُّ","line":14,"type":"word"},{"id":"11:120:15","text":"وَمَوۡعِظَةٌ","line":15,"type":"word"},{"id":"11:120:16","text":"وَّذِكۡرٰى","line":15,"type":"word"},{"id":"11:120:17","text":"لِلۡمُؤۡمِنِيۡنَ‏","line":15,"type":"word"},{"id":"11:120:18","text":"١٢٠","line":15,"type":"end"}]},{"key":"11:121","chapter":11,"words":[{"id":"11:121:1","text":"وَقُلْ","line":15,"type":"word"},{"id":"11:121:2","text":"لِّـلَّذِيۡنَ","line":15,"type":"word"},{"id":"11:121:3","text":"لَا","line":15,"type":"word"},{"id":"11:121:4","text":"يُؤۡمِنُوۡنَ","line":15,"type":"word"},{"id":"11:121:5","text":"اعۡمَلُوۡا","line":15,"type":"word"},{"id":"11:121:6","text":"عَلٰى","line":16,"type":"word"},{"id":"11:121:7","text":"مَكَانَتِكُمۡؕ","line":16,"type":"word"},{"id":"11:121:8","text":"اِنَّا","line":16,"type":"word"},{"id":"11:121:9","text":"عٰمِلُوۡنَۙ‏","line":16,"type":"word"},{"id":"11:121:10","text":"١٢١","line":16,"type":"end"}]},{"key":"11:122","chapter":11,"words":[{"id":"11:122:1","text":"وَانْـتَظِرُوۡا​ ۚ","line":16,"type":"word"},{"id":"11:122:2","text":"اِنَّا","line":16,"type":"word"},{"id":"11:122:3","text":"مُنۡتَظِرُوۡنَ‏","line":16,"type":"word"},{"id":"11:122:4","text":"١٢٢","line":16,"type":"end"}]},{"key":"11:123","chapter":11,"words":[{"id":"11:123:1","text":"وَلِلّٰهِ","line":16,"type":"word"},{"id":"11:123:2","text":"غَيۡبُ","line":1,"type":"word"},{"id":"11:123:3","text":"السَّمٰوٰتِ","line":1,"type":"word"},{"id":"11:123:4","text":"وَالۡاَرۡضِ","line":1,"type":"word"},{"id":"11:123:5","text":"وَاِلَيۡهِ","line":1,"type":"word"},{"id":"11:123:6","text":"يُرۡجَعُ","line":1,"type":"word"},{"id":"11:123:7","text":"الۡاَمۡرُ","line":1,"type":"word"},{"id":"11:123:8","text":"كُلُّهٗ","line":1,"type":"word"},{"id":"11:123:9","text":"فَاعۡبُدۡهُ","line":1,"type":"word"},{"id":"11:123:10","text":"وَتَوَكَّلۡ","line":2,"type":"word"},{"id":"11:123:11","text":"عَلَيۡهِ​ؕ","line":2,"type":"word"},{"id":"11:123:12","text":"وَمَا","line":2,"type":"word"},{"id":"11:123:13","text":"رَبُّكَ","line":2,"type":"word"},{"id":"11:123:14","text":"بِغَافِلٍ","line":2,"type":"word"},{"id":"11:123:15","text":"عَمَّا","line":2,"type":"word"},{"id":"11:123:16","text":"تَعۡمَلُوۡنَ‏ ﻿﻿","line":2,"type":"word"},{"id":"11:123:17","text":"١٢٣","line":2,"type":"end"}]}]}