{"page":499,"juz":28,"verses":[{"key":"61:12","chapter":61,"words":[{"id":"61:12:1","text":"يَغۡفِرۡ","line":16,"type":"word"},{"id":"61:12:2","text":"لَـكُمۡ","line":16,"type":"word"},{"id":"61:12:3","text":"ذُنُوۡبَكُمۡ","line":16,"type":"word"},{"id":"61:12:4","text":"وَيُدۡخِلۡكُمۡ","line":16,"type":"word"},{"id":"61:12:5","text":"جَنّٰتٍ","line":16,"type":"word"},{"id":"61:12:6","text":"تَجۡرِىۡ","line":16,"type":"word"},{"id":"61:12:7","text":"مِنۡ","line":16,"type":"word"},{"id":"61:12:8","text":"تَحۡتِهَا","line":16,"type":"word"},{"id":"61:12:9","text":"الۡاَنۡهٰرُ","line":1,"type":"word"},{"id":"61:12:10","text":"وَمَسٰكِنَ","line":1,"type":"word"},{"id":"61:12:11","text":"طَيِّبَةً","line":1,"type":"word"},{"id":"61:12:12","text":"فِىۡ","line":1,"type":"word"},{"id":"61:12:13","text":"جَنّٰتِ","line":1,"type":"word"},{"id":"61:12:14","text":"عَدۡنٍ​ؕ","line":1,"type":"word"},{"id":"61:12:15","text":"ذٰلِكَ","line":1,"type":"word"},{"id":"61:12:16","text":"الۡفَوۡزُ","line":1,"type":"word"},{"id":"61:12:17","text":"الۡعَظِيۡمُۙ‏ ﻿﻿","line":1,"type":"word"},{"id":"61:12:18","text":"١٢","line":1,"type":"end"}]},{"key":"61:13","chapter":61,"words":[{"id":"61:13:1","text":"وَاُخۡرٰى","line":2,"type":"word"},{"id":"61:13:2","text":"تُحِبُّوۡنَهَا​ ؕ","line":2,"type":"word"},{"id":"61:13:3","text":"نَصۡرٌ","line":2,"type":"word"},{"id":"61:13:4","text":"مِّنَ","line":2,"type":"word"},{"id":"61:13:5","text":"اللّٰهِ","line":2,"type":"word"},{"id":"61:13:6","text":"وَفَـتۡحٌ","line":2,"type":"word"},{"id":"61:13:7","text":"قَرِيۡبٌ​ ؕ","line":2,"type":"word"},{"id":"61:13:8","text":"وَبَشِّرِ","line":2,"type":"word"},{"id":"61:13:9","text":"الۡمُؤۡمِنِيۡنَ‏","line":3,"type":"word"},{"id":"61:13:10","text":"١٣","line":3,"type":"end"}]},{"key":"61:14","chapter":61,"words":[{"id":"61:14:1","text":"يٰۤاَيُّهَا","line":3,"type":"word"},{"id":"61:14:2","text":"الَّذِيۡنَ","line":3,"type":"word"},{"id":"61:14:3","text":"اٰمَنُوۡا","line":3,"type":"word"},{"id":"61:14:4","text":"كُوۡنُوۡۤا","line":3,"type":"word"},{"id":"61:14:5","text":"اَنۡصَارَ","line":3,"type":"word"},{"id":"61:14:6","text":"اللّٰهِ","line":3,"type":"word"},{"id":"61:14:7","text":"كَمَا","line":3,"type":"word"},{"id":"61:14:8","text":"قَالَ","line":3,"type":"word"},{"id":"61:14:9","text":"عِيۡسَى","line":4,"type":"word"},{"id":"61:14:10","text":"ابۡنُ","line":4,"type":"word"},{"id":"61:14:11","text":"مَرۡيَمَ","line":4,"type":"word"},{"id":"61:14:12","text":"لِلۡحَوٰارِيّٖنَ","line":4,"type":"word"},{"id":"61:14:13","text":"مَنۡ","line":4,"type":"word"},{"id":"61:14:14","text":"اَنۡصَارِىۡۤ","line":4,"type":"word"},{"id":"61:14:15","text":"اِلَى","line":4,"type":"word"},{"id":"61:14:16","text":"اللّٰهِ​ؕ","line":4,"type":"word"},{"id":"61:14:17","text":"قَالَ","line":4,"type":"word"},{"id":"61:14:18","text":"الۡحَـوٰرِيُّوۡنَ","line":5,"type":"word"},{"id":"61:14:19","text":"نَحۡنُ","line":5,"type":"word"},{"id":"61:14:20","text":"اَنۡصَارُ","line":5,"type":"word"},{"id":"61:14:21","text":"اللّٰهِ​","line":5,"type":"word"},{"id":"61:14:22","text":"فَاٰمَنَتۡ","line":5,"type":"word"},{"id":"61:14:23","text":"طَّآٮِٕفَةٌ","line":5,"type":"word"},{"id":"61:14:24","text":"مِّنۡۢ","line":5,"type":"word"},{"id":"61:14:25","text":"بَنِىۡۤ","line":5,"type":"word"},{"id":"61:14:26","text":"اِسۡرَآءِيۡلَ","line":6,"type":"word"},{"id":"61:14:27","text":"وَكَفَرَتۡ","line":6,"type":"word"},{"id":"61:14:28","text":"طَّآٮِٕفَةٌ ۚ","line":6,"type":"word"},{"id":"61:14:29","text":"فَاَيَّدۡنَا","line":6,"type":"word"},{"id":"61:14:30","text":"الَّذِيۡنَ","line":6,"type":"word"},{"id":"61:14:31","text":"اٰمَنُوۡا","line":6,"type":"word"},{"id":"61:14:32","text":"عَلٰى","line":6,"type":"word"},{"id":"61:14:33","text":"عَدُوِّهِمۡ","line":7,"type":"word"},{"id":"61:14:34","text":"فَاَصۡبَحُوۡا","line":7,"type":"word"},{"id":"61:14:35","text":"ظٰهِرِيۡنَ‏","line":7,"type":"word"},{"id":"61:14:36","text":"١٤","line":7,"type":"end"}]},{"key":"62:1","chapter":62,"words":[{"id":"62:1:1","text":"يُسَبِّحُ","line":10,"type":"word"},{"id":"62:1:2","text":"لِلّٰهِ","line":10,"type":"word"},{"id":"62:1:3","text":"مَا","line":10,"type":"word"},{"id":"62:1:4","text":"فِى","line":10,"type":"word"},{"id":"62:1:5","text":"السَّمٰوٰتِ","line":10,"type":"word"},{"id":"62:1:6","text":"وَمَا","line":10,"type":"word"},{"id":"62:1:7","text":"فِى","line":10,"type":"word"},{"id":"62:1:8","text":"الۡاَرۡضِ","line":10,"type":"word"},{"id":"62:1:9","text":"الۡمَلِكِ","line":10,"type":"word"},{"id":"62:1:10","text":"الۡقُدُّوۡسِ","line":10,"type":"word"},{"id":"62:1:11","text":"الۡعَزِيۡزِ","line":11,"type":"word"},{"id":"62:1:12","text":"الۡحَكِيۡمِ‏","line":11,"type":"word"},{"id":"62:1:13","text":"١","line":11,"type":"end"}]},{"key":"62:2","chapter":62,"words":[{"id":"62:2:1","text":"هُوَ","line":11,"type":"word"},{"id":"62:2:2","text":"الَّذِىۡ","line":11,"type":"word"},{"id":"62:2:3","text":"بَعَثَ","line":11,"type":"word"},{"id":"62:2:4","text":"فِى","line":11,"type":"word"},{"id":"62:2:5","text":"الۡاُمِّيّٖنَ","line":11,"type":"word"},{"id":"62:2:6","text":"رَسُوۡلًا","line":11,"type":"word"},{"id":"62:2:7","text":"مِّنۡهُمۡ","line":11,"type":"word"},{"id":"62:2:8","text":"يَتۡلُوۡا","line":12,"type":"word"},{"id":"62:2:9","text":"عَلَيۡهِمۡ","line":12,"type":"word"},{"id":"62:2:10","text":"اٰيٰتِهٖ","line":12,"type":"word"},{"id":"62:2:11","text":"وَيُزَكِّيۡهِمۡ","line":12,"type":"word"},{"id":"62:2:12","text":"وَيُعَلِّمُهُمُ","line":12,"type":"word"},{"id":"62:2:13","text":"الۡكِتٰبَ","line":12,"type":"word"},{"id":"62:2:14","text":"وَالۡحِكۡمَةَ","line":12,"type":"word"},{"id":"62:2:15","text":"وَاِنۡ","line":13,"type":"word"},{"id":"62:2:16","text":"كَانُوۡا","line":13,"type":"word"},{"id":"62:2:17","text":"مِنۡ","line":13,"type":"word"},{"id":"62:2:18","text":"قَبۡلُ","line":13,"type":"word"},{"id":"62:2:19","text":"لَفِىۡ","line":13,"type":"word"},{"id":"62:2:20","text":"ضَلٰلٍ","line":13,"type":"word"},{"id":"62:2:21","text":"مُّبِيۡنٍۙ‏","line":13,"type":"word"},{"id":"62:2:22","text":"٢","line":13,"type":"end"}]},{"key":"62:3","chapter":62,"words":[{"id":"62:3:1","text":"وَّاٰخَرِيۡنَ","line":13,"type":"word"},{"id":"62:3:2","text":"مِنۡهُمۡ","line":13,"type":"word"},{"id":"62:3:3","text":"لَمَّا","line":13,"type":"word"},{"id":"62:3:4","text":"يَلۡحَقُوۡا","line":14,"type":"word"},{"id":"62:3:5","text":"بِهِمۡ​ؕ","line":14,"type":"word"},{"id":"62:3:6","text":"وَهُوَ","line":14,"type":"word"},{"id":"62:3:7","text":"الۡعَزِيۡزُ","line":14,"type":"word"},{"id":"62:3:8","text":"الۡحَكِيۡمُ‏ ﻿﻿","line":14,"type":"word"},{"id":"62:3:9","text":"٣","line":14,"type":"end"}]},{"key":"62:4","chapter":62,"words":[{"id":"62:4:1","text":"ذٰ لِكَ","line":14,"type":"word"},{"id":"62:4:2","text":"فَضۡلُ","line":14,"type":"word"},{"id":"62:4:3","text":"اللّٰهِ","line":14,"type":"word"},{"id":"62:4:4","text":"يُؤۡتِيۡهِ","line":14,"type":"word"},{"id":"62:4:5","text":"مَنۡ","line":15,"type":"word"},{"id":"62:4:6","text":"يَّشَآءُ​ ؕ","line":15,"type":"word"},{"id":"62:4:7","text":"وَاللّٰهُ","line":15,"type":"word"},{"id":"62:4:8","text":"ذُو","line":15,"type":"word"},{"id":"62:4:9","text":"الۡفَضۡلِ","line":15,"type":"word"},{"id":"62:4:10","text":"الۡعَظِيۡمِ‏","line":15,"type":"word"},{"id":"62:4:11","text":"٤","line":15,"type":"end"}]},{"key":"62:5","chapter":62,"words":[{"id":"62:5:1","text":"مَثَلُ","line":15,"type":"word"},{"id":"62:5:2","text":"الَّذِيۡنَ","line":15,"type":"word"},{"id":"62:5:3","text":"حُمِّلُوا","line":15,"type":"word"},{"id":"62:5:4","text":"التَّوۡرٰٮةَ","line":16,"type":"word"},{"id":"62:5:5","text":"ثُمَّ","line":16,"type":"word"},{"id":"62:5:6","text":"لَمۡ","line":16,"type":"word"},{"id":"62:5:7","text":"يَحۡمِلُوۡهَا","line":16,"type":"word"},{"id":"62:5:8","text":"كَمَثَلِ","line":16,"type":"word"},{"id":"62:5:9","text":"الۡحِمَارِ","line":16,"type":"word"},{"id":"62:5:10","text":"يَحۡمِلُ","line":16,"type":"word"},{"id":"62:5:11","text":"اَسۡفَارًا​ ؕ","line":16,"type":"word"},{"id":"62:5:12","text":"بِئۡسَ","line":16,"type":"word"},{"id":"62:5:13","text":"مَثَلُ","line":1,"type":"word"},{"id":"62:5:14","text":"الۡقَوۡمِ","line":1,"type":"word"},{"id":"62:5:15","text":"الَّذِيۡنَ","line":1,"type":"word"},{"id":"62:5:16","text":"كَذَّبُوۡا","line":1,"type":"word"},{"id":"62:5:17","text":"بِاٰيٰتِ","line":1,"type":"word"},{"id":"62:5:18","text":"اللّٰهِ ​ؕ","line":1,"type":"word"},{"id":"62:5:19","text":"وَاللّٰهُ","line":1,"type":"word"},{"id":"62:5:20","text":"لَا","line":1,"type":"word"},{"id":"62:5:21","text":"يَهۡدِى","line":1,"type":"word"},{"id":"62:5:22","text":"الۡقَوۡمَ","line":1,"type":"word"},{"id":"62:5:23","text":"الظّٰلِمِيۡنَ‏","line":2,"type":"word"},{"id":"62:5:24","text":"٥","line":2,"type":"end"}]}]}