{"page":98,"juz":6,"verses":[{"key":"5:6","chapter":5,"words":[{"id":"5:6:1","text":"يٰۤـاَيُّهَا","line":11,"type":"word"},{"id":"5:6:2","text":"الَّذِيۡنَ","line":11,"type":"word"},{"id":"5:6:3","text":"اٰمَنُوۡۤا","line":11,"type":"word"},{"id":"5:6:4","text":"اِذَا","line":12,"type":"word"},{"id":"5:6:5","text":"قُمۡتُمۡ","line":12,"type":"word"},{"id":"5:6:6","text":"اِلَى","line":12,"type":"word"},{"id":"5:6:7","text":"الصَّلٰوةِ","line":12,"type":"word"},{"id":"5:6:8","text":"فَاغۡسِلُوۡا","line":12,"type":"word"},{"id":"5:6:9","text":"وُجُوۡهَكُمۡ","line":12,"type":"word"},{"id":"5:6:10","text":"وَاَيۡدِيَكُمۡ","line":12,"type":"word"},{"id":"5:6:11","text":"اِلَى","line":12,"type":"word"},{"id":"5:6:12","text":"الۡمَرَافِقِ","line":13,"type":"word"},{"id":"5:6:13","text":"وَامۡسَحُوۡا","line":13,"type":"word"},{"id":"5:6:14","text":"بِرُءُوۡسِكُمۡ","line":13,"type":"word"},{"id":"5:6:15","text":"وَاَرۡجُلَكُمۡ","line":13,"type":"word"},{"id":"5:6:16","text":"اِلَى","line":13,"type":"word"},{"id":"5:6:17","text":"الۡـكَعۡبَيۡنِ​ ؕ","line":13,"type":"word"},{"id":"5:6:18","text":"وَاِنۡ","line":13,"type":"word"},{"id":"5:6:19","text":"كُنۡتُمۡ","line":14,"type":"word"},{"id":"5:6:20","text":"جُنُبًا","line":14,"type":"word"},{"id":"5:6:21","text":"فَاطَّهَّرُوۡا​ ؕ","line":14,"type":"word"},{"id":"5:6:22","text":"وَاِنۡ","line":14,"type":"word"},{"id":"5:6:23","text":"كُنۡتُمۡ","line":14,"type":"word"},{"id":"5:6:24","text":"مَّرۡضَىٰۤ","line":14,"type":"word"},{"id":"5:6:25","text":"اَوۡ","line":14,"type":"word"},{"id":"5:6:26","text":"عَلٰى","line":14,"type":"word"},{"id":"5:6:27","text":"سَفَرٍ","line":14,"type":"word"},{"id":"5:6:28","text":"اَوۡ","line":14,"type":"word"},{"id":"5:6:29","text":"جَآءَ","line":15,"type":"word"},{"id":"5:6:30","text":"اَحَدٌ","line":15,"type":"word"},{"id":"5:6:31","text":"مِّنۡكُمۡ","line":15,"type":"word"},{"id":"5:6:32","text":"مِّنَ","line":15,"type":"word"},{"id":"5:6:33","text":"الۡغَآٮِٕطِ","line":15,"type":"word"},{"id":"5:6:34","text":"اَوۡ","line":15,"type":"word"},{"id":"5:6:35","text":"لٰمَسۡتُمُ","line":15,"type":"word"},{"id":"5:6:36","text":"النِّسَآءَ","line":15,"type":"word"},{"id":"5:6:37","text":"فَلَمۡ","line":15,"type":"word"},{"id":"5:6:38","text":"تَجِدُوۡا","line":15,"type":"word"},{"id":"5:6:39","text":"مَآءً","line":16,"type":"word"},{"id":"5:6:40","text":"فَتَيَمَّمُوۡا","line":16,"type":"word"},{"id":"5:6:41","text":"صَعِيۡدًا","line":16,"type":"word"},{"id":"5:6:42","text":"طَيِّبًا","line":16,"type":"word"},{"id":"5:6:43","text":"فَامۡسَحُوۡا","line":16,"type":"word"},{"id":"5:6:44","text":"بِوُجُوۡهِكُمۡ","line":16,"type":"word"},{"id":"5:6:45","text":"وَاَيۡدِيۡكُمۡ","line":16,"type":"word"},{"id":"5:6:46","text":"مِّنۡهُ​ ؕ","line":1,"type":"word"},{"id":"5:6:47","text":"مَا","line":1,"type":"word"},{"id":"5:6:48","text":"يُرِيۡدُ","line":1,"type":"word"},{"id":"5:6:49","text":"اللّٰهُ","line":1,"type":"word"},{"id":"5:6:50","text":"لِيَجۡعَلَ","line":1,"type":"word"},{"id":"5:6:51","text":"عَلَيۡكُمۡ","line":1,"type":"word"},{"id":"5:6:52","text":"مِّنۡ","line":1,"type":"word"},{"id":"5:6:53","text":"حَرَجٍ","line":1,"type":"word"},{"id":"5:6:54","text":"وَّلٰـكِنۡ","line":1,"type":"word"},{"id":"5:6:55","text":"يُّرِيۡدُ","line":1,"type":"word"},{"id":"5:6:56","text":"لِيُطَهِّرَكُمۡ","line":2,"type":"word"},{"id":"5:6:57","text":"وَ لِيُتِمَّ","line":2,"type":"word"},{"id":"5:6:58","text":"نِعۡمَتَهٗ","line":2,"type":"word"},{"id":"5:6:59","text":"عَلَيۡكُمۡ","line":2,"type":"word"},{"id":"5:6:60","text":"لَعَلَّكُمۡ","line":2,"type":"word"},{"id":"5:6:61","text":"تَشۡكُرُوۡنَ‏","line":2,"type":"word"},{"id":"5:6:62","text":"٦","line":2,"type":"end"}]},{"key":"5:7","chapter":5,"words":[{"id":"5:7:1","text":"وَاذْکُرُوْ","line":3,"type":"word"},{"id":"5:7:2","text":"انِعْمَةَ","line":3,"type":"word"},{"id":"5:7:3","text":"اللهِ","line":3,"type":"word"},{"id":"5:7:4","text":"عَلَیْکُمْ","line":3,"type":"word"},{"id":"5:7:5","text":"وَمِیْثَاقَهُ","line":3,"type":"word"},{"id":"5:7:6","text":"الَّذِیْ","line":3,"type":"word"},{"id":"5:7:7","text":"وَاثَقَکُمْ","line":3,"type":"word"},{"id":"5:7:8","text":"بِهۤ ۙ","line":3,"type":"word"},{"id":"5:7:9","text":"اِذْ","line":4,"type":"word"},{"id":"5:7:10","text":"قُلْتُمْ","line":4,"type":"word"},{"id":"5:7:11","text":"سَمِعْنَا","line":4,"type":"word"},{"id":"5:7:12","text":"وَاَطَعْنَا","line":4,"type":"word"},{"id":"5:7:13","text":"وَاتَّقُوا","line":4,"type":"word"},{"id":"5:7:14","text":"اللهَ ؕ","line":4,"type":"word"},{"id":"5:7:15","text":"اِنَّ","line":4,"type":"word"},{"id":"5:7:16","text":"اللهَ","line":4,"type":"word"},{"id":"5:7:17","text":"عَلِیْمٌۢ","line":4,"type":"word"},{"id":"5:7:18","text":"بِذَاتِ","line":4,"type":"word"},{"id":"5:7:19","text":"الصُّدُوْرِ‏","line":5,"type":"word"},{"id":"5:7:20","text":"٧","line":5,"type":"end"}]},{"key":"5:8","chapter":5,"words":[{"id":"5:8:1","text":"يٰۤـاَيُّهَا","line":5,"type":"word"},{"id":"5:8:2","text":"الَّذِيۡنَ","line":5,"type":"word"},{"id":"5:8:3","text":"اٰمَنُوۡا","line":5,"type":"word"},{"id":"5:8:4","text":"كُوۡنُوۡا","line":5,"type":"word"},{"id":"5:8:5","text":"قَوَّا امِيۡنَ","line":5,"type":"word"},{"id":"5:8:6","text":"لِلّٰهِ","line":5,"type":"word"},{"id":"5:8:7","text":"شُهَدَآءَ","line":5,"type":"word"},{"id":"5:8:8","text":"بِالۡقِسۡطِ​","line":6,"type":"word"},{"id":"5:8:9","text":"وَلَا","line":6,"type":"word"},{"id":"5:8:10","text":"يَجۡرِمَنَّكُمۡ","line":6,"type":"word"},{"id":"5:8:11","text":"شَنَاٰنُ","line":6,"type":"word"},{"id":"5:8:12","text":"قَوۡمٍ","line":6,"type":"word"},{"id":"5:8:13","text":"عَلٰٓى","line":6,"type":"word"},{"id":"5:8:14","text":"اَ لَّا","line":6,"type":"word"},{"id":"5:8:15","text":"تَعۡدِلُوۡا​ ؕ","line":6,"type":"word"},{"id":"5:8:16","text":"اِعۡدِلُوۡا","line":7,"type":"word"},{"id":"5:8:17","text":"هُوَ","line":7,"type":"word"},{"id":"5:8:18","text":"اَقۡرَبُ","line":7,"type":"word"},{"id":"5:8:19","text":"لِلتَّقۡوٰى​","line":7,"type":"word"},{"id":"5:8:20","text":"وَاتَّقُوا","line":7,"type":"word"},{"id":"5:8:21","text":"اللّٰهَ​ ؕ","line":7,"type":"word"},{"id":"5:8:22","text":"اِنَّ","line":7,"type":"word"},{"id":"5:8:23","text":"اللّٰهَ","line":7,"type":"word"},{"id":"5:8:24","text":"خَبِيۡرٌۢ","line":7,"type":"word"},{"id":"5:8:25","text":"بِمَا","line":8,"type":"word"},{"id":"5:8:26","text":"تَعۡمَلُوۡنَ‏","line":8,"type":"word"},{"id":"5:8:27","text":"٨","line":8,"type":"end"}]},{"key":"5:9","chapter":5,"words":[{"id":"5:9:1","text":"وَعَدَ","line":8,"type":"word"},{"id":"5:9:2","text":"اللّٰهُ","line":8,"type":"word"},{"id":"5:9:3","text":"الَّذِيۡنَ","line":8,"type":"word"},{"id":"5:9:4","text":"اٰمَنُوۡا","line":8,"type":"word"},{"id":"5:9:5","text":"وَعَمِلُوا","line":8,"type":"word"},{"id":"5:9:6","text":"الصّٰلِحٰتِ​ ۙ","line":8,"type":"word"},{"id":"5:9:7","text":"لَهُمۡ","line":9,"type":"word"},{"id":"5:9:8","text":"مَّغۡفِرَةٌ","line":9,"type":"word"},{"id":"5:9:9","text":"وَّاَجۡرٌ","line":9,"type":"word"},{"id":"5:9:10","text":"عَظِيۡمٌ‏","line":9,"type":"word"},{"id":"5:9:11","text":"٩","line":9,"type":"end"}]},{"key":"5:10","chapter":5,"words":[{"id":"5:10:1","text":"وَالَّذِيۡنَ","line":9,"type":"word"},{"id":"5:10:2","text":"كَفَرُوۡا","line":9,"type":"word"},{"id":"5:10:3","text":"وَكَذَّبُوۡا","line":9,"type":"word"},{"id":"5:10:4","text":"بِاٰيٰتِنَاۤ","line":9,"type":"word"},{"id":"5:10:5","text":"اُولٰٓٮِٕكَ","line":10,"type":"word"},{"id":"5:10:6","text":"اَصۡحٰبُ","line":10,"type":"word"},{"id":"5:10:7","text":"الۡجَحِيۡمِ‏ ﻿﻿","line":10,"type":"word"},{"id":"5:10:8","text":"١٠","line":10,"type":"end"}]},{"key":"5:11","chapter":5,"words":[{"id":"5:11:1","text":"يٰۤـاَيُّهَا","line":10,"type":"word"},{"id":"5:11:2","text":"الَّذِيۡنَ","line":10,"type":"word"},{"id":"5:11:3","text":"اٰمَنُوا","line":10,"type":"word"},{"id":"5:11:4","text":"اذۡكُرُوۡا","line":10,"type":"word"},{"id":"5:11:5","text":"نِعۡمَتَ","line":10,"type":"word"},{"id":"5:11:6","text":"اللّٰهِ","line":11,"type":"word"},{"id":"5:11:7","text":"عَلَيۡكُمۡ","line":11,"type":"word"},{"id":"5:11:8","text":"اِذۡ","line":11,"type":"word"},{"id":"5:11:9","text":"هَمَّ","line":11,"type":"word"},{"id":"5:11:10","text":"قَوۡمٌ","line":11,"type":"word"},{"id":"5:11:11","text":"اَنۡ","line":11,"type":"word"},{"id":"5:11:12","text":"يَّبۡسُطُوۡۤا","line":11,"type":"word"},{"id":"5:11:13","text":"اِلَيۡكُمۡ","line":11,"type":"word"},{"id":"5:11:14","text":"اَيۡدِيَهُمۡ","line":11,"type":"word"},{"id":"5:11:15","text":"فَكَفَّ","line":11,"type":"word"},{"id":"5:11:16","text":"اَيۡدِيَهُمۡ","line":12,"type":"word"},{"id":"5:11:17","text":"عَنۡكُمۡ​ۚ","line":12,"type":"word"},{"id":"5:11:18","text":"وَاتَّقُوا","line":12,"type":"word"},{"id":"5:11:19","text":"اللّٰهَ​ ؕ","line":12,"type":"word"},{"id":"5:11:20","text":"وَعَلَى","line":12,"type":"word"},{"id":"5:11:21","text":"اللّٰهِ","line":12,"type":"word"},{"id":"5:11:22","text":"فَلۡيَتَوَكَّلِ","line":12,"type":"word"},{"id":"5:11:23","text":"الۡمُؤۡمِنُوۡنَ‏","line":12,"type":"word"},{"id":"5:11:24","text":"١١","line":12,"type":"end"}]},{"key":"5:12","chapter":5,"words":[{"id":"5:12:1","text":"۞ وَلَقَدۡ","line":13,"type":"word"},{"id":"5:12:2","text":"اَخَذَ","line":13,"type":"word"},{"id":"5:12:3","text":"اللّٰهُ","line":13,"type":"word"},{"id":"5:12:4","text":"مِيۡثَاقَ","line":13,"type":"word"},{"id":"5:12:5","text":"بَنِىۡۤ","line":13,"type":"word"},{"id":"5:12:6","text":"اِسۡرآءِيۡلَ​ۚ","line":13,"type":"word"},{"id":"5:12:7","text":"وَبَعَثۡنَا","line":13,"type":"word"},{"id":"5:12:8","text":"مِنۡهُمُ","line":13,"type":"word"},{"id":"5:12:9","text":"اثۡنَىۡ","line":14,"type":"word"},{"id":"5:12:10","text":"عَشَرَ","line":14,"type":"word"},{"id":"5:12:11","text":"نَقِيۡبًا​ ؕ","line":14,"type":"word"},{"id":"5:12:12","text":"وَقَالَ","line":14,"type":"word"},{"id":"5:12:13","text":"اللّٰهُ","line":14,"type":"word"},{"id":"5:12:14","text":"اِنِّىۡ","line":14,"type":"word"},{"id":"5:12:15","text":"مَعَكُمۡ​ؕ","line":14,"type":"word"},{"id":"5:12:16","text":"لَٮِٕنۡ","line":14,"type":"word"},{"id":"5:12:17","text":"اَقَمۡتُمُ","line":14,"type":"word"},{"id":"5:12:18","text":"الصَّلٰوةَ","line":14,"type":"word"},{"id":"5:12:19","text":"وَاٰتَيۡتُمُ","line":15,"type":"word"},{"id":"5:12:20","text":"الزَّكٰوةَ","line":15,"type":"word"},{"id":"5:12:21","text":"وَاٰمَنۡتُمۡ","line":15,"type":"word"},{"id":"5:12:22","text":"بِرُسُلِىۡ","line":15,"type":"word"},{"id":"5:12:23","text":"وَعَزَّرۡتُمُوۡهُمۡ","line":15,"type":"word"},{"id":"5:12:24","text":"وَاَقۡرَضۡتُمُ","line":15,"type":"word"},{"id":"5:12:25","text":"اللّٰهَ","line":16,"type":"word"},{"id":"5:12:26","text":"قَرۡضًا","line":16,"type":"word"},{"id":"5:12:27","text":"حَسَنًا","line":16,"type":"word"},{"id":"5:12:28","text":"لَّاُكَفِّرَنَّ","line":16,"type":"word"},{"id":"5:12:29","text":"عَنۡكُمۡ","line":16,"type":"word"},{"id":"5:12:30","text":"سَيِّاٰتِكُمۡ","line":16,"type":"word"},{"id":"5:12:31","text":"وَلَاُدۡخِلَـنَّكُمۡ","line":16,"type":"word"},{"id":"5:12:32","text":"جَنّٰتٍ","line":1,"type":"word"},{"id":"5:12:33","text":"تَجۡرِىۡ","line":1,"type":"word"},{"id":"5:12:34","text":"مِنۡ","line":1,"type":"word"},{"id":"5:12:35","text":"تَحۡتِهَا","line":1,"type":"word"},{"id":"5:12:36","text":"الۡاَنۡهٰرُ​ۚ","line":1,"type":"word"},{"id":"5:12:37","text":"فَمَنۡ","line":1,"type":"word"},{"id":"5:12:38","text":"كَفَرَ","line":1,"type":"word"},{"id":"5:12:39","text":"بَعۡدَ","line":1,"type":"word"},{"id":"5:12:40","text":"ذٰ لِكَ","line":1,"type":"word"},{"id":"5:12:41","text":"مِنۡكُمۡ","line":1,"type":"word"},{"id":"5:12:42","text":"فَقَدۡ","line":2,"type":"word"},{"id":"5:12:43","text":"ضَلَّ","line":2,"type":"word"},{"id":"5:12:44","text":"سَوَآءَ","line":2,"type":"word"},{"id":"5:12:45","text":"السَّبِيۡلِ‏","line":2,"type":"word"},{"id":"5:12:46","text":"١٢","line":2,"type":"end"}]}]}