{"page":135,"juz":7,"verses":[{"key":"6:59","chapter":6,"words":[{"id":"6:59:1","text":"۞ وَعِنۡدَهٗ","line":1,"type":"word"},{"id":"6:59:2","text":"مَفَاتِحُ","line":1,"type":"word"},{"id":"6:59:3","text":"الۡغَيۡبِ","line":1,"type":"word"},{"id":"6:59:4","text":"لَا","line":1,"type":"word"},{"id":"6:59:5","text":"يَعۡلَمُهَاۤ","line":1,"type":"word"},{"id":"6:59:6","text":"اِلَّا","line":1,"type":"word"},{"id":"6:59:7","text":"هُوَ​ؕ","line":1,"type":"word"},{"id":"6:59:8","text":"وَيَعۡلَمُ","line":1,"type":"word"},{"id":"6:59:9","text":"مَا","line":1,"type":"word"},{"id":"6:59:10","text":"فِى","line":1,"type":"word"},{"id":"6:59:11","text":"الۡبَرِّ","line":1,"type":"word"},{"id":"6:59:12","text":"وَالۡبَحۡرِ​ؕ","line":2,"type":"word"},{"id":"6:59:13","text":"وَمَا","line":2,"type":"word"},{"id":"6:59:14","text":"تَسۡقُطُ","line":2,"type":"word"},{"id":"6:59:15","text":"مِنۡ","line":2,"type":"word"},{"id":"6:59:16","text":"وَّرَقَةٍ","line":2,"type":"word"},{"id":"6:59:17","text":"اِلَّا","line":2,"type":"word"},{"id":"6:59:18","text":"يَعۡلَمُهَا","line":2,"type":"word"},{"id":"6:59:19","text":"وَلَا","line":2,"type":"word"},{"id":"6:59:20","text":"حَبَّةٍ","line":2,"type":"word"},{"id":"6:59:21","text":"فِىۡ","line":2,"type":"word"},{"id":"6:59:22","text":"ظُلُمٰتِ","line":2,"type":"word"},{"id":"6:59:23","text":"الۡاَرۡضِ","line":3,"type":"word"},{"id":"6:59:24","text":"وَلَا","line":3,"type":"word"},{"id":"6:59:25","text":"رَطۡبٍ","line":3,"type":"word"},{"id":"6:59:26","text":"وَّلَا","line":3,"type":"word"},{"id":"6:59:27","text":"يَابِسٍ","line":3,"type":"word"},{"id":"6:59:28","text":"اِلَّا","line":3,"type":"word"},{"id":"6:59:29","text":"فِىۡ","line":3,"type":"word"},{"id":"6:59:30","text":"كِتٰبٍ","line":3,"type":"word"},{"id":"6:59:31","text":"مُّبِيۡنٍ‏ ﻿﻿","line":3,"type":"word"},{"id":"6:59:32","text":"٥٩","line":3,"type":"end"}]},{"key":"6:60","chapter":6,"words":[{"id":"6:60:1","text":"وَهُوَ","line":3,"type":"word"},{"id":"6:60:2","text":"الَّذِىۡ","line":3,"type":"word"},{"id":"6:60:3","text":"يَتَوَفّٰٮكُمۡ","line":4,"type":"word"},{"id":"6:60:4","text":"بِالَّيۡلِ","line":4,"type":"word"},{"id":"6:60:5","text":"وَ يَعۡلَمُ","line":4,"type":"word"},{"id":"6:60:6","text":"مَا","line":4,"type":"word"},{"id":"6:60:7","text":"جَرَحۡتُمۡ","line":4,"type":"word"},{"id":"6:60:8","text":"بِالنَّهَارِ","line":4,"type":"word"},{"id":"6:60:9","text":"ثُمَّ","line":4,"type":"word"},{"id":"6:60:10","text":"يَـبۡعَثُكُمۡ","line":4,"type":"word"},{"id":"6:60:11","text":"فِيۡهِ","line":4,"type":"word"},{"id":"6:60:12","text":"لِيُقۡضٰٓى","line":4,"type":"word"},{"id":"6:60:13","text":"اَجَلٌ","line":5,"type":"word"},{"id":"6:60:14","text":"مُّسَمًّى​ۚ","line":5,"type":"word"},{"id":"6:60:15","text":"ثُمَّ","line":5,"type":"word"},{"id":"6:60:16","text":"اِلَيۡهِ","line":5,"type":"word"},{"id":"6:60:17","text":"مَرۡجِعُكُمۡ","line":5,"type":"word"},{"id":"6:60:18","text":"ثُمَّ","line":5,"type":"word"},{"id":"6:60:19","text":"يُنَبِّئُكُمۡ","line":5,"type":"word"},{"id":"6:60:20","text":"بِمَا","line":5,"type":"word"},{"id":"6:60:21","text":"كُنۡتُمۡ","line":5,"type":"word"},{"id":"6:60:22","text":"تَعۡمَلُوۡنَ‏","line":5,"type":"word"},{"id":"6:60:23","text":"٦٠","line":5,"type":"end"}]},{"key":"6:61","chapter":6,"words":[{"id":"6:61:1","text":"وَهُوَ","line":6,"type":"word"},{"id":"6:61:2","text":"الۡقَاهِرُ","line":6,"type":"word"},{"id":"6:61:3","text":"فَوۡقَ","line":6,"type":"word"},{"id":"6:61:4","text":"عِبَادِهٖ​","line":6,"type":"word"},{"id":"6:61:5","text":"وَيُرۡسِلُ","line":6,"type":"word"},{"id":"6:61:6","text":"عَلَيۡكُمۡ","line":6,"type":"word"},{"id":"6:61:7","text":"حَفَظَةً  ؕ","line":6,"type":"word"},{"id":"6:61:8","text":"حَتّٰٓى","line":6,"type":"word"},{"id":"6:61:9","text":"اِذَا","line":6,"type":"word"},{"id":"6:61:10","text":"جَآءَ","line":6,"type":"word"},{"id":"6:61:11","text":"اَحَدَكُمُ","line":7,"type":"word"},{"id":"6:61:12","text":"الۡمَوۡتُ","line":7,"type":"word"},{"id":"6:61:13","text":"تَوَفَّتۡهُ","line":7,"type":"word"},{"id":"6:61:14","text":"رُسُلُـنَا","line":7,"type":"word"},{"id":"6:61:15","text":"وَهُمۡ","line":7,"type":"word"},{"id":"6:61:16","text":"لَا","line":7,"type":"word"},{"id":"6:61:17","text":"يُفَرِّطُوۡنَ‏ ﻿﻿","line":7,"type":"word"},{"id":"6:61:18","text":"٦١","line":7,"type":"end"}]},{"key":"6:62","chapter":6,"words":[{"id":"6:62:1","text":"ثُمَّ","line":7,"type":"word"},{"id":"6:62:2","text":"رُدُّوۡۤا","line":7,"type":"word"},{"id":"6:62:3","text":"اِلَى","line":8,"type":"word"},{"id":"6:62:4","text":"اللّٰهِ","line":8,"type":"word"},{"id":"6:62:5","text":"مَوۡلٰٮهُمُ","line":8,"type":"word"},{"id":"6:62:6","text":"الۡحَـقِّ​ؕ","line":8,"type":"word"},{"id":"6:62:7","text":"اَلَا","line":8,"type":"word"},{"id":"6:62:8","text":"لَهُ","line":8,"type":"word"},{"id":"6:62:9","text":"الۡحُكۡمُ","line":8,"type":"word"},{"id":"6:62:10","text":"وَهُوَ","line":8,"type":"word"},{"id":"6:62:11","text":"اَسۡرَعُ","line":8,"type":"word"},{"id":"6:62:12","text":"الۡحَاسِبِيۡنَ‏","line":8,"type":"word"},{"id":"6:62:13","text":"٦٢","line":8,"type":"end"}]},{"key":"6:63","chapter":6,"words":[{"id":"6:63:1","text":"قُلۡ","line":9,"type":"word"},{"id":"6:63:2","text":"مَنۡ","line":9,"type":"word"},{"id":"6:63:3","text":"يُّنَجِّيۡكُمۡ","line":9,"type":"word"},{"id":"6:63:4","text":"مِّنۡ","line":9,"type":"word"},{"id":"6:63:5","text":"ظُلُمٰتِ","line":9,"type":"word"},{"id":"6:63:6","text":"الۡبَرِّ","line":9,"type":"word"},{"id":"6:63:7","text":"وَالۡبَحۡرِ","line":9,"type":"word"},{"id":"6:63:8","text":"تَدۡعُوۡنَهٗ","line":9,"type":"word"},{"id":"6:63:9","text":"تَضَرُّعًا","line":9,"type":"word"},{"id":"6:63:10","text":"وَّخُفۡيَةً ۚ","line":10,"type":"word"},{"id":"6:63:11","text":"لَٮِٕنۡ","line":10,"type":"word"},{"id":"6:63:12","text":"اَنۡجٰٮنَا","line":10,"type":"word"},{"id":"6:63:13","text":"مِنۡ","line":10,"type":"word"},{"id":"6:63:14","text":"هٰذِهٖ","line":10,"type":"word"},{"id":"6:63:15","text":"لَـنَكُوۡنَنَّ","line":10,"type":"word"},{"id":"6:63:16","text":"مِنَ","line":10,"type":"word"},{"id":"6:63:17","text":"الشّٰكِرِيۡنَ‏ ﻿﻿","line":10,"type":"word"},{"id":"6:63:18","text":"٦٣","line":10,"type":"end"}]},{"key":"6:64","chapter":6,"words":[{"id":"6:64:1","text":"قُلِ","line":10,"type":"word"},{"id":"6:64:2","text":"اللّٰهُ","line":10,"type":"word"},{"id":"6:64:3","text":"يُنَجِّيۡكُمۡ","line":11,"type":"word"},{"id":"6:64:4","text":"مِّنۡهَا","line":11,"type":"word"},{"id":"6:64:5","text":"وَمِنۡ","line":11,"type":"word"},{"id":"6:64:6","text":"كُلِّ","line":11,"type":"word"},{"id":"6:64:7","text":"كَرۡبٍ","line":11,"type":"word"},{"id":"6:64:8","text":"ثُمَّ","line":11,"type":"word"},{"id":"6:64:9","text":"اَنۡـتُمۡ","line":11,"type":"word"},{"id":"6:64:10","text":"تُشۡرِكُوۡنَ‏ ﻿﻿","line":11,"type":"word"},{"id":"6:64:11","text":"٦٤","line":11,"type":"end"}]},{"key":"6:65","chapter":6,"words":[{"id":"6:65:1","text":"قُلۡ","line":11,"type":"word"},{"id":"6:65:2","text":"هُوَ","line":11,"type":"word"},{"id":"6:65:3","text":"الۡقَادِرُ","line":11,"type":"word"},{"id":"6:65:4","text":"عَلٰٓى","line":12,"type":"word"},{"id":"6:65:5","text":"اَنۡ","line":12,"type":"word"},{"id":"6:65:6","text":"يَّبۡعَثَ","line":12,"type":"word"},{"id":"6:65:7","text":"عَلَيۡكُمۡ","line":12,"type":"word"},{"id":"6:65:8","text":"عَذَابًا","line":12,"type":"word"},{"id":"6:65:9","text":"مِّنۡ","line":12,"type":"word"},{"id":"6:65:10","text":"فَوۡقِكُمۡ","line":12,"type":"word"},{"id":"6:65:11","text":"اَوۡ","line":12,"type":"word"},{"id":"6:65:12","text":"مِنۡ","line":12,"type":"word"},{"id":"6:65:13","text":"تَحۡتِ","line":12,"type":"word"},{"id":"6:65:14","text":"اَرۡجُلِكُمۡ","line":12,"type":"word"},{"id":"6:65:15","text":"اَوۡ","line":13,"type":"word"},{"id":"6:65:16","text":"يَلۡبِسَكُمۡ","line":13,"type":"word"},{"id":"6:65:17","text":"شِيَـعًا","line":13,"type":"word"},{"id":"6:65:18","text":"وَّيُذِيۡقَ","line":13,"type":"word"},{"id":"6:65:19","text":"بَعۡضَكُمۡ","line":13,"type":"word"},{"id":"6:65:20","text":"بَاۡسَ","line":13,"type":"word"},{"id":"6:65:21","text":"بَعۡضٍ​ؕ","line":13,"type":"word"},{"id":"6:65:22","text":"اُنْظُرۡ","line":13,"type":"word"},{"id":"6:65:23","text":"كَيۡفَ","line":13,"type":"word"},{"id":"6:65:24","text":"نُصَرِّفُ","line":14,"type":"word"},{"id":"6:65:25","text":"الۡاٰيٰتِ","line":14,"type":"word"},{"id":"6:65:26","text":"لَعَلَّهُمۡ","line":14,"type":"word"},{"id":"6:65:27","text":"يَفۡقَهُوۡنَ‏","line":14,"type":"word"},{"id":"6:65:28","text":"٦٥","line":14,"type":"end"}]},{"key":"6:66","chapter":6,"words":[{"id":"6:66:1","text":"وَكَذَّبَ","line":14,"type":"word"},{"id":"6:66:2","text":"بِهٖ","line":14,"type":"word"},{"id":"6:66:3","text":"قَوۡمُكَ","line":14,"type":"word"},{"id":"6:66:4","text":"وَهُوَ","line":14,"type":"word"},{"id":"6:66:5","text":"الۡحَـقُّ​ ؕ","line":14,"type":"word"},{"id":"6:66:6","text":"قُلْ","line":15,"type":"word"},{"id":"6:66:7","text":"لَّسۡتُ","line":15,"type":"word"},{"id":"6:66:8","text":"عَلَيۡكُمۡ","line":15,"type":"word"},{"id":"6:66:9","text":"بِوَكِيۡلٍؕ‏ ﻿﻿","line":15,"type":"word"},{"id":"6:66:10","text":"٦٦","line":15,"type":"end"}]},{"key":"6:67","chapter":6,"words":[{"id":"6:67:1","text":"لِّـكُلِّ","line":15,"type":"word"},{"id":"6:67:2","text":"نَبَاٍ","line":15,"type":"word"},{"id":"6:67:3","text":"مُّسۡتَقَرٌّ​","line":15,"type":"word"},{"id":"6:67:4","text":"وَّسَوۡفَ","line":15,"type":"word"},{"id":"6:67:5","text":"تَعۡلَمُوۡنَ‏","line":15,"type":"word"},{"id":"6:67:6","text":"٦٧","line":15,"type":"end"}]}]}