{"page":5,"juz":1,"verses":[{"key":"2:24","chapter":2,"words":[{"id":"2:24:1","text":"فَاِنۡ","line":1,"type":"word"},{"id":"2:24:2","text":"لَّمۡ","line":1,"type":"word"},{"id":"2:24:3","text":"تَفۡعَلُوۡا","line":1,"type":"word"},{"id":"2:24:4","text":"وَلَنۡ","line":1,"type":"word"},{"id":"2:24:5","text":"تَفۡعَلُوۡا","line":1,"type":"word"},{"id":"2:24:6","text":"فَاتَّقُوۡا","line":1,"type":"word"},{"id":"2:24:7","text":"النَّارَ","line":1,"type":"word"},{"id":"2:24:8","text":"الَّتِىۡ","line":1,"type":"word"},{"id":"2:24:9","text":"وَقُوۡدُهَا","line":1,"type":"word"},{"id":"2:24:10","text":"النَّاسُ","line":2,"type":"word"},{"id":"2:24:11","text":"وَالۡحِجَارَةُ  ۖۚ","line":2,"type":"word"},{"id":"2:24:12","text":"اُعِدَّتۡ","line":2,"type":"word"},{"id":"2:24:13","text":"لِلۡكٰفِرِيۡنَ‏","line":2,"type":"word"},{"id":"2:24:14","text":"٢٤","line":2,"type":"end"}]},{"key":"2:25","chapter":2,"words":[{"id":"2:25:1","text":"وَبَشِّرِ","line":2,"type":"word"},{"id":"2:25:2","text":"الَّذِيۡنَ","line":2,"type":"word"},{"id":"2:25:3","text":"اٰمَنُوۡا","line":2,"type":"word"},{"id":"2:25:4","text":"وَ عَمِلُوا","line":3,"type":"word"},{"id":"2:25:5","text":"الصّٰلِحٰتِ","line":3,"type":"word"},{"id":"2:25:6","text":"اَنَّ","line":3,"type":"word"},{"id":"2:25:7","text":"لَهُمۡ","line":3,"type":"word"},{"id":"2:25:8","text":"جَنّٰتٍ","line":3,"type":"word"},{"id":"2:25:9","text":"تَجۡرِىۡ","line":3,"type":"word"},{"id":"2:25:10","text":"مِنۡ","line":3,"type":"word"},{"id":"2:25:11","text":"تَحۡتِهَا","line":3,"type":"word"},{"id":"2:25:12","text":"الۡاَنۡهٰرُ​ؕ","line":3,"type":"word"},{"id":"2:25:13","text":"ڪُلَّمَا","line":3,"type":"word"},{"id":"2:25:14","text":"رُزِقُوۡا","line":4,"type":"word"},{"id":"2:25:15","text":"مِنۡهَا","line":4,"type":"word"},{"id":"2:25:16","text":"مِنۡ","line":4,"type":"word"},{"id":"2:25:17","text":"ثَمَرَةٍ","line":4,"type":"word"},{"id":"2:25:18","text":"رِّزۡقًا ​ۙ","line":4,"type":"word"},{"id":"2:25:19","text":"قَالُوۡا","line":4,"type":"word"},{"id":"2:25:20","text":"هٰذَا","line":4,"type":"word"},{"id":"2:25:21","text":"الَّذِىۡ","line":4,"type":"word"},{"id":"2:25:22","text":"رُزِقۡنَا","line":4,"type":"word"},{"id":"2:25:23","text":"مِنۡ","line":4,"type":"word"},{"id":"2:25:24","text":"قَبۡلُ","line":5,"type":"word"},{"id":"2:25:25","text":"وَاُتُوۡا","line":5,"type":"word"},{"id":"2:25:26","text":"بِهٖ","line":5,"type":"word"},{"id":"2:25:27","text":"مُتَشَابِهًا ​ؕ","line":5,"type":"word"},{"id":"2:25:28","text":"وَلَهُمۡ","line":5,"type":"word"},{"id":"2:25:29","text":"فِيۡهَآ","line":5,"type":"word"},{"id":"2:25:30","text":"اَزۡوَاجٌ","line":5,"type":"word"},{"id":"2:25:31","text":"مُّطَهَّرَةٌ ​ۙ","line":5,"type":"word"},{"id":"2:25:32","text":"وَّهُمۡ","line":5,"type":"word"},{"id":"2:25:33","text":"فِيۡهَا","line":5,"type":"word"},{"id":"2:25:34","text":"خٰلِدُوۡنَ‏","line":6,"type":"word"},{"id":"2:25:35","text":"٢٥","line":6,"type":"end"}]},{"key":"2:26","chapter":2,"words":[{"id":"2:26:1","text":"۞ اِنَّ","line":6,"type":"word"},{"id":"2:26:2","text":"اللّٰهَ","line":6,"type":"word"},{"id":"2:26:3","text":"لَا","line":6,"type":"word"},{"id":"2:26:4","text":"يَسۡتَحۡـىٖۤ","line":6,"type":"word"},{"id":"2:26:5","text":"اَنۡ","line":6,"type":"word"},{"id":"2:26:6","text":"يَّضۡرِبَ","line":6,"type":"word"},{"id":"2:26:7","text":"مَثَلًا","line":6,"type":"word"},{"id":"2:26:8","text":"مَّا","line":6,"type":"word"},{"id":"2:26:9","text":"بَعُوۡضَةً","line":6,"type":"word"},{"id":"2:26:10","text":"فَمَا","line":7,"type":"word"},{"id":"2:26:11","text":"فَوۡقَهَا ​ؕ","line":7,"type":"word"},{"id":"2:26:12","text":"فَاَمَّا","line":7,"type":"word"},{"id":"2:26:13","text":"الَّذِيۡنَ","line":7,"type":"word"},{"id":"2:26:14","text":"اٰمَنُوۡا","line":7,"type":"word"},{"id":"2:26:15","text":"فَيَعۡلَمُوۡنَ","line":7,"type":"word"},{"id":"2:26:16","text":"اَنَّهُ","line":7,"type":"word"},{"id":"2:26:17","text":"الۡحَـقُّ","line":7,"type":"word"},{"id":"2:26:18","text":"مِنۡ","line":7,"type":"word"},{"id":"2:26:19","text":"رَّبِّهِمۡ​ۚ","line":8,"type":"word"},{"id":"2:26:20","text":"وَاَمَّا","line":8,"type":"word"},{"id":"2:26:21","text":"الَّذِيۡنَ","line":8,"type":"word"},{"id":"2:26:22","text":"ڪَفَرُوۡا","line":8,"type":"word"},{"id":"2:26:23","text":"فَيَقُوۡلُوۡنَ","line":8,"type":"word"},{"id":"2:26:24","text":"مَاذَآ","line":8,"type":"word"},{"id":"2:26:25","text":"اَرَادَ","line":8,"type":"word"},{"id":"2:26:26","text":"اللّٰهُ","line":8,"type":"word"},{"id":"2:26:27","text":"بِهٰذَا","line":8,"type":"word"},{"id":"2:26:28","text":"مَثَلًا ۘ","line":9,"type":"word"},{"id":"2:26:29","text":"يُضِلُّ","line":9,"type":"word"},{"id":"2:26:30","text":"بِهٖ","line":9,"type":"word"},{"id":"2:26:31","text":"ڪَثِيۡرًا","line":9,"type":"word"},{"id":"2:26:32","text":"وَّيَهۡدِىۡ","line":9,"type":"word"},{"id":"2:26:33","text":"بِهٖ","line":9,"type":"word"},{"id":"2:26:34","text":"كَثِيۡرًا ​ؕ","line":9,"type":"word"},{"id":"2:26:35","text":"وَمَا","line":9,"type":"word"},{"id":"2:26:36","text":"يُضِلُّ","line":9,"type":"word"},{"id":"2:26:37","text":"بِهٖۤ","line":9,"type":"word"},{"id":"2:26:38","text":"اِلَّا","line":9,"type":"word"},{"id":"2:26:39","text":"الۡفٰسِقِيۡنَۙ","line":10,"type":"word"},{"id":"2:26:40","text":"٢٦","line":10,"type":"end"}]},{"key":"2:27","chapter":2,"words":[{"id":"2:27:1","text":"الَّذِيۡنَ","line":10,"type":"word"},{"id":"2:27:2","text":"يَنۡقُضُوۡنَ","line":10,"type":"word"},{"id":"2:27:3","text":"عَهۡدَ","line":10,"type":"word"},{"id":"2:27:4","text":"اللّٰهِ","line":10,"type":"word"},{"id":"2:27:5","text":"مِنۡۢ","line":10,"type":"word"},{"id":"2:27:6","text":"بَعۡدِ","line":10,"type":"word"},{"id":"2:27:7","text":"مِيۡثَاقِهٖ","line":10,"type":"word"},{"id":"2:27:8","text":"وَيَقۡطَعُوۡنَ","line":11,"type":"word"},{"id":"2:27:9","text":"مَآ","line":11,"type":"word"},{"id":"2:27:10","text":"اَمَرَ","line":11,"type":"word"},{"id":"2:27:11","text":"اللّٰهُ","line":11,"type":"word"},{"id":"2:27:12","text":"بِهٖۤ","line":11,"type":"word"},{"id":"2:27:13","text":"اَنۡ","line":11,"type":"word"},{"id":"2:27:14","text":"يُّوۡصَلَ","line":11,"type":"word"},{"id":"2:27:15","text":"وَيُفۡسِدُوۡنَ","line":11,"type":"word"},{"id":"2:27:16","text":"فِى","line":11,"type":"word"},{"id":"2:27:17","text":"الۡاَرۡضِ​ؕ","line":11,"type":"word"},{"id":"2:27:18","text":"اُولٰٓٮِٕكَ","line":12,"type":"word"},{"id":"2:27:19","text":"هُمُ","line":12,"type":"word"},{"id":"2:27:20","text":"الۡخٰسِرُوۡنَ‏","line":12,"type":"word"},{"id":"2:27:21","text":"٢٧","line":12,"type":"end"}]},{"key":"2:28","chapter":2,"words":[{"id":"2:28:1","text":"كَيۡفَ","line":12,"type":"word"},{"id":"2:28:2","text":"تَكۡفُرُوۡنَ","line":12,"type":"word"},{"id":"2:28:3","text":"بِاللّٰهِ","line":12,"type":"word"},{"id":"2:28:4","text":"وَڪُنۡتُمۡ","line":12,"type":"word"},{"id":"2:28:5","text":"اَمۡوَاتًا","line":12,"type":"word"},{"id":"2:28:6","text":"فَاَحۡيَاکُمۡ​ۚ","line":13,"type":"word"},{"id":"2:28:7","text":"ثُمَّ","line":13,"type":"word"},{"id":"2:28:8","text":"يُمِيۡتُكُمۡ","line":13,"type":"word"},{"id":"2:28:9","text":"ثُمَّ","line":13,"type":"word"},{"id":"2:28:10","text":"يُحۡيِيۡكُمۡ","line":13,"type":"word"},{"id":"2:28:11","text":"ثُمَّ","line":13,"type":"word"},{"id":"2:28:12","text":"اِلَيۡهِ","line":13,"type":"word"},{"id":"2:28:13","text":"تُرۡجَعُوۡنَ‏","line":13,"type":"word"},{"id":"2:28:14","text":"٢٨","line":13,"type":"end"}]},{"key":"2:29","chapter":2,"words":[{"id":"2:29:1","text":"هُوَ","line":14,"type":"word"},{"id":"2:29:2","text":"الَّذِىۡ","line":14,"type":"word"},{"id":"2:29:3","text":"خَلَقَ","line":14,"type":"word"},{"id":"2:29:4","text":"لَـكُمۡ","line":14,"type":"word"},{"id":"2:29:5","text":"مَّا","line":14,"type":"word"},{"id":"2:29:6","text":"فِى","line":14,"type":"word"},{"id":"2:29:7","text":"الۡاَرۡضِ","line":14,"type":"word"},{"id":"2:29:8","text":"جَمِيۡعًا","line":14,"type":"word"},{"id":"2:29:9","text":"ثُمَّ","line":14,"type":"word"},{"id":"2:29:10","text":"اسۡتَوٰۤى","line":14,"type":"word"},{"id":"2:29:11","text":"اِلَى","line":14,"type":"word"},{"id":"2:29:12","text":"السَّمَآءِ","line":15,"type":"word"},{"id":"2:29:13","text":"فَسَوّٰٮهُنَّ","line":15,"type":"word"},{"id":"2:29:14","text":"سَبۡعَ","line":15,"type":"word"},{"id":"2:29:15","text":"سَمٰوٰتٍ​ؕ","line":15,"type":"word"},{"id":"2:29:16","text":"وَهُوَ","line":15,"type":"word"},{"id":"2:29:17","text":"بِكُلِّ","line":15,"type":"word"},{"id":"2:29:18","text":"شَىۡءٍ","line":15,"type":"word"},{"id":"2:29:19","text":"عَلِيۡمٌ‏ ﻿﻿","line":15,"type":"word"},{"id":"2:29:20","text":"٢٩","line":15,"type":"end"}]}]}